omq/__init__.py
omq/constants.py
omq/omq.py
omq-0.5.5.dist-info/LICENSE
omq-0.5.5.dist-info/METADATA
omq-0.5.5.dist-info/WHEEL
omq-0.5.5.dist-info/top_level.txt
omq-0.5.5.dist-info/RECORD
