Metadata-Version: 2.1
Name: omq
Version: 0.5.5
Summary: A package wrap NNG
Home-page: https://github.com/rty813/omq
Author: rty813
Author-email: zjy523213189zjy@gmail.com
License: UNKNOWN
Platform: UNKNOWN
Classifier: Programming Language :: Python :: 3
Classifier: License :: OSI Approved :: MIT License
Classifier: Operating System :: OS Independent
Requires-Python: >=3.6
Requires-Dist: pynng
